{"inkVersion":21,"root":[["^「喂？你怎麼站著不動？趕快進教室吧～」","#","^speaker:學姊","/#","#","^portrait:default","/#","#","^layout:left","/#","#","^scene:\"player_turn\"","/#","\n","^（家豪緩緩摘下耳機，看著前方的人群。）","#","^speaker:家豪","/#","#","^portrait:default","/#","#","^layout:left","/#","\n","ev","str","^「嗯……我馬上來。」","/str","/ev",{"*":"0.c-0","flg":20},"ev","str","^「剛剛……有點恍神。」","/str","/ev",{"*":"0.c-1","flg":20},"ev","str","^「……妳有聽到剛剛的聲音嗎？」","/str","/ev",{"*":"0.c-2","flg":20},{"c-0":["#","^speaker:家豪","/#","#","^portrait:default","/#","#","^layout:left","/#","\n","^「好啦，別再發呆了～」","#","^speaker:學姊","/#","#","^portrait:default","/#","#","^layout:left","/#","\n",{"->":"After_Questions"},{"->":"0.g-0"},{"#f":5}],"c-1":["#","^speaker:家豪","/#","#","^portrait:default","/#","#","^layout:left","/#","\n","^「哈，第一天就緊張成這樣？」","#","^speaker:學姊","/#","#","^portrait:default","/#","#","^layout:left","/#","\n",{"->":"After_Questions"},{"->":"0.g-0"},{"#f":5}],"c-2":["#","^speaker:家豪","/#","#","^portrait:default","/#","#","^layout:left","/#","\n","^「聲音？你該不會在開玩笑吧？」","#","^speaker:學姊","/#","#","^portrait:default","/#","#","^layout:left","/#","\n",{"->":"After_Questions"},{"->":"0.g-0"},{"#f":5}],"g-0":["done",{"#f":5}]}],"done",{"After_Questions":["^「走啦～不然等一下老師來會被唸喔。」","#","^speaker:學姊","/#","#","^portrait:default","/#","#","^layout:left","/#","\n","^（家豪低頭看著自己的手，手上似乎還殘留著微弱的光。）","#","^speaker:家豪","/#","#","^portrait:default","/#","#","^layout:left","/#","\n","end",{"#f":1}],"#f":1}],"listDefs":{}}